dexc-0.4.0.dist-info/METADATA
dexc-0.4.0.dist-info/WHEEL
dexc-0.4.0.dist-info/RECORD
dexc/__init__.py
dexc/autoinstall.py
dexc/extract.py
dexc/inspector.py
dexc/lib.py
dexc/options.py
dexc/render.py
dexc/util.py
dexc/vendor.py
dexc/compression/__init__.py
dexc/compression/greedy.py
dexc/compression/optimal.py
dexc/hooks/__init__.py
dexc/hooks/errors.py
dexc/hooks/warnings.py
