Metadata-Version: 2.4
Name: dexc
Version: 0.4.0
Requires-Python: ~=3.11
Summary: Exception formatter
License-Expression: EUPL-1.2
Project-URL: Repository, https://github.com/slietar/dexc
